{"save-time":1741381944,"time-offset":false,"files":["/Users/jacob.romero/workspace/test/wandb/run-20250306_172005-2smy2z1q/logs/*"],"file-states":{"/Users/jacob.romero/Library/Caches/wandb/logs/core-debug-20250306_172005.log":{"visible":true},"/Users/jacob.romero/workspace/test/wandb/run-20250306_172005-2smy2z1q/logs/debug-internal.log":{"visible":true},"/Users/jacob.romero/workspace/test/wandb/run-20250306_172005-2smy2z1q/logs/debug.log":{"visible":true}},"views":{"log":{"top_line":0,"focused_line":46,"search":"resume","word_wrap":false,"filtering":true,"commands":[]},"text":{"top_line":-1,"search":"","word_wrap":false,"filtering":true,"commands":[]},"help":{"top_line":-1,"search":"","word_wrap":false,"filtering":true,"commands":[]},"histogram":{"top_line":-1,"search":"","word_wrap":false,"filtering":true,"commands":[]},"db":{"top_line":-1,"search":"","word_wrap":false,"filtering":true,"commands":[]},"schema":{"top_line":-1,"search":"","word_wrap":false},"pretty":{"top_line":-1,"search":"","word_wrap":false},"spectro":{"top_line":-1,"search":"","word_wrap":false,"filtering":true,"commands":[]},"timeline":{"top_line":-1,"search":"","word_wrap":false,"filtering":true,"commands":[]}}}