{"save-time":1743619870,"time-offset":false,"files":["/Users/jacob.romero/workspace/test/wandb/run-20250402_115011-rfnwost5/logs/*"],"file-states":{"/Users/jacob.romero/Library/Caches/wandb/logs/core-debug-20250402_115010.log":{"visible":true},"/Users/jacob.romero/workspace/test/wandb/run-20250402_115011-rfnwost5/logs/debug-internal.log":{"visible":true},"/Users/jacob.romero/workspace/test/wandb/run-20250402_115011-rfnwost5/logs/debug.log":{"visible":true}},"views":{"log":{"top_line":-1,"focused_line":55,"search":"uploading live","word_wrap":false,"filtering":true,"commands":[]},"text":{"top_line":-1,"search":"","word_wrap":false,"filtering":true,"commands":[]},"help":{"top_line":-1,"search":"","word_wrap":false,"filtering":true,"commands":[]},"histogram":{"top_line":-1,"search":"","word_wrap":false,"filtering":true,"commands":[]},"db":{"top_line":-1,"search":"","word_wrap":false,"filtering":true,"commands":[]},"schema":{"top_line":-1,"search":"","word_wrap":false},"pretty":{"top_line":-1,"search":"","word_wrap":false},"spectro":{"top_line":-1,"search":"","word_wrap":false,"filtering":true,"commands":[]},"timeline":{"top_line":-1,"search":"","word_wrap":false,"filtering":true,"commands":[]}}}